example.py
pynvml.py
nvidia_ml_py-11.515.0.dist-info/METADATA
nvidia_ml_py-11.515.0.dist-info/WHEEL
nvidia_ml_py-11.515.0.dist-info/top_level.txt
nvidia_ml_py-11.515.0.dist-info/RECORD
